{
   "schemes": {
      "Push": {
         "build": {
            "targets": {
               "Push": "all"
            }
         },
         "run": {
            "config": "Debug"
         },
         "test": {
            "config": "Debug"
         },
         "profile": {
            "config": "Release"
         },
         "analyze": {
            "config": "Debug"
         },
         "archive": {
            "config": "Release",
            "customArchiveName": "Push",
            "revealArchiveInOrganizer": true
         }
      }
   }
}
